skinpy/__init__.py
skinpy/__main__.py
skinpy/exception.py
skinpy/render.py
skinpy/skin.py
skinpy/types.py
skinpy_extended-1.0.1.dist-info/METADATA
skinpy_extended-1.0.1.dist-info/WHEEL
skinpy_extended-1.0.1.dist-info/entry_points.txt
skinpy_extended-1.0.1.dist-info/RECORD
