Metadata-Version: 2.1
Name: skinpy-extended
Version: 1.0.1
Summary: A Python library to generate, reconstruct, and map Minecraft skins between 2D textures and 3D renders
Author-Email: Bonenk <bonynakhale@gmail.com>, Tim Martin <tim@timmart.in>, Steven Van Ingelgem <steven@vaningelgem.be>
License: MIT
Classifier: Programming Language :: Python :: 3.9
Classifier: Programming Language :: Python :: 3.10
Classifier: Programming Language :: Python :: 3.11
Classifier: Programming Language :: Python :: 3.12
Classifier: License :: OSI Approved :: MIT License
Project-URL: repository, https://github.com/Bonenk/skinpy-extended
Requires-Python: >=3.9
Requires-Dist: attrs>=23.2.0
Requires-Dist: numpy>=1.26.4
Requires-Dist: Pillow>=10.3.0
Requires-Dist: click>=8.1.7
Requires-Dist: twine>=6.2.0
